{
  "profession": "minecraft:fisherman",
  "removeOtherTrades": true,
  "trades": [
    {
      "offer": {
        "itemKey": "minecraft:emerald",
        "amount": 1,
        "priceModifier": 0
      },
      "request": {
        "itemKey": "minecraft:string",
        "amount": 20,
        "priceModifier": 0
      },
      "tradeExp": 4,
      "maxUses": 16,
      "priceMultiplier": 0.2,
      "demand": 0,
      "tradeLevel": 1,
      "UTID": "minecraft:fisherman_emerald_for_string_0"
    },
    {
      "offer": {
        "itemKey": "minecraft:emerald",
        "amount": 1,
        "priceModifier": 0
      },
      "request": {
        "itemKey": "minecraft:kelp",
        "amount": 40,
        "priceModifier": 0
      },
      "tradeExp": 4,
      "maxUses": 16,
      "priceMultiplier": 0.2,
      "demand": 0,
      "tradeLevel": 1,
      "UTID": "minecraft:fisherman_emerald_for_kelp"
    },
    {
      "offer": {
        "itemKey": "minecraft:cod",
        "amount": 4,
        "priceModifier": 0
      },
      "request": {
        "itemKey": "minecraft:emerald",
        "amount": 12,
        "priceModifier": 0
      },
      "tradeExp": 3,
      "maxUses": 16,
      "priceMultiplier": 0.2,
      "demand": 0,
      "tradeLevel": 1,
      "UTID": "minecraft:fisherman_cod_for_emerald"
    },
    {
      "offer": {
        "itemKey": "minecraft:cod_bucket",
        "amount": 1,
        "priceModifier": 0
      },
      "request": {
        "itemKey": "minecraft:emerald",
        "amount": 6,
        "priceModifier": 0
      },
      "tradeExp": 3,
      "maxUses": 4,
      "priceMultiplier": 0.2,
      "demand": 0,
      "tradeLevel": 1,
      "UTID": "minecraft:fisherman_cod_bucket_for_emerald_0"
    },
    {
      "offer": {
        "itemKey": "minecraft:salmon",
        "amount": 2,
        "priceModifier": 0
      },
      "request": {
        "itemKey": "minecraft:emerald",
        "amount": 12,
        "priceModifier": 0
      },
      "tradeExp": 8,
      "maxUses": 16,
      "priceMultiplier": 0.2,
      "demand": 0,
      "tradeLevel": 2,
      "UTID": "minecraft:fisherman_salmon_for_emerald"
    },
    {
      "offer": {
        "itemKey": "minecraft:salmon_bucket",
        "amount": 1,
        "priceModifier": 0
      },
      "request": {
        "itemKey": "minecraft:emerald",
        "amount": 10,
        "priceModifier": 0
      },
      "tradeExp": 8,
      "maxUses": 4,
      "priceMultiplier": 0.2,
      "demand": 0,
      "tradeLevel": 2,
      "UTID": "minecraft:fisherman_salmon_bucket_for_emerald"
    },
    {
      "offer": {
        "itemKey": "minecraft:campfire",
        "amount": 4,
        "priceModifier": 0
      },
      "request": {
        "itemKey": "minecraft:emerald",
        "amount": 4,
        "priceModifier": 0
      },
      "tradeExp": 5,
      "maxUses": 12,
      "priceMultiplier": 0.2,
      "demand": 0,
      "tradeLevel": 2,
      "UTID": "minecraft:fisherman_campfire_for_emerald_0"
    },
    {
      "offer": {
        "itemKey": "architects_palette:cod_log",
        "amount": 8,
        "priceModifier": 0
      },
      "request": {
        "itemKey": "minecraft:emerald",
        "amount": 8,
        "priceModifier": 0
      },
      "tradeExp": 4,
      "maxUses": 6,
      "priceMultiplier": 0.2,
      "demand": 0,
      "tradeLevel": 2,
      "UTID": "minecraft:fisherman_cod_log_for_emerald_0"
    },
    {
      "offer": {
        "itemKey": "architects_palette:salmon_log",
        "amount": 8,
        "priceModifier": 0
      },
      "request": {
        "itemKey": "minecraft:emerald",
        "amount": 12,
        "priceModifier": 0
      },
      "tradeExp": 4,
      "maxUses": 6,
      "priceMultiplier": 0.2,
      "demand": 0,
      "tradeLevel": 2,
      "UTID": "minecraft:fisherman_salmon_log_for_emerald_0"
    },
    {
      "offer": {
        "itemKey": "villagersellanimals:crate_fox_pup",
        "amount": 1,
        "priceModifier": 0
      },
      "request": {
        "itemKey": "minecraft:emerald",
        "amount": 32,
        "priceModifier": 0
      },
      "tradeExp": 5,
      "maxUses": 4,
      "priceMultiplier": 0.2,
      "demand": 0,
      "tradeLevel": 2,
      "UTID": "minecraft:fisherman_crate_fox_pup_for_emerald_0"
    },
    {
      "offer": {
        "itemKey": "upgrade_aquatic:perch",
        "amount": 4,
        "priceModifier": 0
      },
      "request": {
        "itemKey": "minecraft:emerald",
        "amount": 16,
        "priceModifier": 0
      },
      "tradeExp": 12,
      "maxUses": 16,
      "priceMultiplier": 0.2,
      "demand": 0,
      "tradeLevel": 2,
      "UTID": "minecraft:fisherman_perch_for_emerald"
    },
    {
      "offer": {
        "itemKey": "upgrade_aquatic:perch_bucket",
        "amount": 1,
        "priceModifier": 0
      },
      "request": {
        "itemKey": "minecraft:emerald",
        "amount": 12,
        "priceModifier": 0
      },
      "tradeExp": 12,
      "maxUses": 4,
      "priceMultiplier": 0.2,
      "demand": 0,
      "tradeLevel": 2,
      "UTID": "minecraft:fisherman_perch_bucket_for_emerald"
    },
    {
      "offer": {
        "itemKey": "minecraft:fishing_rod",
        "amount": 1,
        "priceModifier": 0
      },
      "request": {
        "itemKey": "minecraft:emerald",
        "amount": 4,
        "priceModifier": 0
      },
      "tradeExp": 10,
      "maxUses": 3,
      "priceMultiplier": 0.2,
      "demand": 0,
      "tradeLevel": 3,
      "UTID": "minecraft:fisherman_fishing_rod_for_emerald_0"
    },
    {
      "offer": {
        "itemKey": "upgrade_aquatic:pike",
        "amount": 2,
        "priceModifier": 0
      },
      "request": {
        "itemKey": "minecraft:emerald",
        "amount": 16,
        "priceModifier": 0
      },
      "tradeExp": 12,
      "maxUses": 16,
      "priceMultiplier": 0.2,
      "demand": 0,
      "tradeLevel": 3,
      "UTID": "minecraft:fisherman_pike_for_emerald"
    },
    {
      "offer": {
        "itemKey": "upgrade_aquatic:pike_bucket",
        "amount": 1,
        "priceModifier": 0
      },
      "request": {
        "itemKey": "minecraft:emerald",
        "amount": 14,
        "priceModifier": 0
      },
      "tradeExp": 12,
      "maxUses": 4,
      "priceMultiplier": 0.2,
      "demand": 0,
      "tradeLevel": 3,
      "UTID": "minecraft:fisherman_pike_bucket_for_emerald"
    },
    {
      "offer": {
        "itemKey": "minecraft:emerald",
        "amount": 1,
        "priceModifier": 0
      },
      "request": {
        "itemKey": "minecraft:tropical_fish",
        "amount": 3,
        "priceModifier": 0
      },
      "tradeExp": 30,
      "maxUses": 12,
      "priceMultiplier": 0.2,
      "demand": 0,
      "tradeLevel": 4,
      "UTID": "minecraft:fisherman_emerald_for_tropical_fish_0"
    },
    {
      "offer": {
        "itemKey": "upgrade_aquatic:lionfish",
        "amount": 2,
        "priceModifier": 0
      },
      "request": {
        "itemKey": "minecraft:emerald",
        "amount": 16,
        "priceModifier": 0
      },
      "tradeExp": 16,
      "maxUses": 16,
      "priceMultiplier": 0.2,
      "demand": 0,
      "tradeLevel": 4,
      "UTID": "minecraft:fisherman_lionfish_for_emerald"
    },
    {
      "offer": {
        "itemKey": "upgrade_aquatic:lionfish_bucket",
        "amount": 1,
        "priceModifier": 0
      },
      "request": {
        "itemKey": "minecraft:emerald",
        "amount": 12,
        "priceModifier": 0
      },
      "tradeExp": 16,
      "maxUses": 4,
      "priceMultiplier": 0.2,
      "demand": 0,
      "tradeLevel": 4,
      "UTID": "minecraft:fisherman_lionfish_bucket_for_emerald"
    },
    {
      "offer": {
        "itemKey": "minecraft:emerald",
        "amount": 1,
        "priceModifier": 0
      },
      "request": {
        "itemKey": "minecraft:pufferfish",
        "amount": 2,
        "priceModifier": 0
      },
      "tradeExp": 30,
      "maxUses": 12,
      "priceMultiplier": 0.2,
      "demand": 0,
      "tradeLevel": 5,
      "UTID": "minecraft:fisherman_emerald_for_pufferfish_0"
    },
    {
      "offer": {
        "itemKey": "minecraft:emerald",
        "amount": 1,
        "priceModifier": 0
      },
      "request": {
        "itemKey": "miners_delight:squid",
        "amount": 3,
        "priceModifier": 0
      },
      "tradeExp": 30,
      "maxUses": 12,
      "priceMultiplier": 0.2,
      "demand": 0,
      "tradeLevel": 5,
      "UTID": "minecraft:fisherman_emerald_for_squid"
    },
    {
      "offer": {
        "itemKey": "minecraft:pufferfish_bucket",
        "amount": 1,
        "priceModifier": 0
      },
      "request": {
        "itemKey": "minecraft:emerald",
        "amount": 24,
        "priceModifier": 0
      },
      "tradeExp": 30,
      "maxUses": 4,
      "priceMultiplier": 0.2,
      "demand": 0,
      "tradeLevel": 5,
      "UTID": "minecraft:fisherman_pufferfish_bucket_for_emerald"
    },
    {
      "offer": {
        "itemKey": "minecraft:spyglass",
        "amount": 1,
        "priceModifier": 0
      },
      "request": {
        "itemKey": "minecraft:emerald",
        "amount": 24,
        "priceModifier": 0
      },
      "tradeExp": 30,
      "maxUses": 4,
      "priceMultiplier": 0.2,
      "demand": 0,
      "tradeLevel": 5,
      "UTID": "minecraft:fisherman_spyglass_for_emerald"
    }
  ]
}