{
  "parent": "raspberryflavoured:mech_press",
  "criteria": {
    "0": {
      "conditions": {
        "block": "create:mechanical_mixer"
      },
      "trigger": "minecraft:placed_block"
    }
  },
  "display": {
    "announce_to_chat": true,
    "description": {
      "color": "#DBA213",
      "text": "Place down a mechanical mixer over a basin to start mixing ingredients or materials - this is the most resource efficient way to get andesite alloy, and is also the only way to brew your own potions!"
    },
    "frame": "task",
    "hidden": false,
    "icon": {
      "item": "create:mechanical_mixer"
    },
    "show_toast": true,
    "title": {
      "text": "Mixin' It Up!"
    }
  },
  "requirements": [
    [
      "0"
    ]
  ]
}