{
  "parent": "raspberry_flavoured:main/silver",
  "criteria": {
    "0": {
      "conditions": {
        "items": [
          {
            "items": [
              "oreganized:electrum_ingot"
            ]
          }
        ]
      },
      "trigger": "minecraft:inventory_changed"
    }
  },
  "display": {
    "title": {
      "translate": "advancements.rf.main.electrum.title"
    },
    "description": {
      "color": "#ED3D69",
      "translate": "advancements.rf.main.electrum.description"
    },
    "icon": {
      "item": "oreganized:electrum_ingot"
    },
    "frame": "challenge",
    "hidden": false,
    "announce_to_chat": true,
    "show_toast": true
  },
  "rewards": {
      "function": "raspberry_flavoured:sound_challenge"
    },
  "requirements": [
    [
      "0"
    ]
  ]
}