{
  "parent": "raspberry_flavoured:main/obsidian",
  "criteria": {
    "0": {
      "trigger": "minecraft:impossible"
    }
  },
  "display": {
    "title": {
      "translate": "advancements.rf.main.potion.title"
    },
    "description": {
      "color": "#ED3D69",
      "translate": "advancements.rf.main.potion.description"
    },
    "icon": {
      "item": "minecraft:potion",
	  "nbt": "{Potion: \"minecraft:swiftness\"}"
    },
    "frame": "goal",
    "hidden": false,
    "announce_to_chat": true,
    "show_toast": true
  },
  "rewards": {
      "function": "raspberry_flavoured:sound_goal"
    },
  "requirements": [
    [
      "0"
    ]
  ]
}